raiiaf/__init__.py
raiiaf/chunks/__init__.py
raiiaf/chunks/env.py
raiiaf/chunks/image.py
raiiaf/chunks/latent.py
raiiaf/chunks/metadata.py
raiiaf/core/__init__.py
raiiaf/core/constants.py
raiiaf/core/exceptions.py
raiiaf/core/header.py
raiiaf/handlers/__init__.py
raiiaf/handlers/file_handler.py
raiiaf-1.1.0.dist-info/licenses/LICENSE
raiiaf-1.1.0.dist-info/METADATA
raiiaf-1.1.0.dist-info/WHEEL
raiiaf-1.1.0.dist-info/top_level.txt
raiiaf-1.1.0.dist-info/RECORD
